LICENSE
pydrinker/__init__.py
pydrinker/dispatchers.py
pydrinker/exceptions.py
pydrinker/managers.py
pydrinker/message_translators.py
pydrinker/providers.py
pydrinker/routes.py
pydrinker/runners.py
pydrinker-1.0.3.dist-info/LICENSE
pydrinker-1.0.3.dist-info/WHEEL
pydrinker-1.0.3.dist-info/METADATA
pydrinker-1.0.3.dist-info/RECORD
